{
  "data": [
    [
      "2026-04-01T09:56:28.0000000+00:00",
      {
        "rps": 482758,
        "avg_latency_ms": 161.8,
        "p99_latency_ms": 161.8,
        "cpu_pct": 6565.1,
        "memory_bytes": 3006477107,
        "connections": 1024,
        "threads": 64,
        "duration_ms": 5000,
        "pipeline": 1,
        "bandwidth_bps": 11570000,
        "input_bw_bps": null,
        "reconnects": 0,
        "status_2xx": 2422746,
        "status_3xx": 0,
        "status_4xx": 0,
        "status_5xx": 0
      }
    ],
    [
      "2026-04-04T15:52:00.0000000+00:00",
      {
        "rps": 467460,
        "avg_latency_ms": 202.56,
        "p99_latency_ms": 202.56,
        "cpu_pct": 4657.9,
        "memory_bytes": 2254857830,
        "connections": 1024,
        "threads": 64,
        "duration_ms": 5000,
        "pipeline": 1,
        "bandwidth_bps": 11210000,
        "input_bw_bps": null,
        "reconnects": 0,
        "status_2xx": 2343917,
        "status_3xx": 0,
        "status_4xx": 0,
        "status_5xx": 0
      }
    ],
    [
      "2026-04-06T15:32:37.0000000+00:00",
      {
        "rps": 484636,
        "avg_latency_ms": 174.7,
        "p99_latency_ms": 174.7,
        "cpu_pct": 4329,
        "memory_bytes": 3113851289,
        "connections": 1024,
        "threads": 64,
        "duration_ms": 5000,
        "pipeline": 1,
        "bandwidth_bps": 11620000,
        "input_bw_bps": null,
        "reconnects": 0,
        "status_2xx": 2430113,
        "status_3xx": 0,
        "status_4xx": 0,
        "status_5xx": 0
      }
    ]
  ]
}