{
  "data": [
    [
      "2026-04-14T23:25:10.0000000+00:00",
      {
        "rps": 490794,
        "avg_latency_ms": 30.28,
        "p99_latency_ms": 773.2,
        "cpu_pct": 6511.1,
        "memory_bytes": 1395864371,
        "connections": 16384,
        "threads": 64,
        "duration_ms": 5000,
        "pipeline": 1,
        "bandwidth_bps": 520620000,
        "input_bw_bps": 36040000,
        "reconnects": 97233,
        "status_2xx": 2453970,
        "status_3xx": 0,
        "status_4xx": 0,
        "status_5xx": 0
      }
    ],
    [
      "2026-04-21T23:28:39.0000000+00:00",
      {
        "rps": 490794,
        "avg_latency_ms": 30.28,
        "p99_latency_ms": 773.2,
        "cpu_pct": 6511.1,
        "memory_bytes": 1395864371,
        "connections": 16384,
        "threads": 64,
        "duration_ms": 5000,
        "pipeline": 1,
        "bandwidth_bps": 520620000,
        "input_bw_bps": 36040000,
        "reconnects": 97233,
        "status_2xx": 2453970,
        "status_3xx": 0,
        "status_4xx": 0,
        "status_5xx": 0
      }
    ],
    [
      "2026-04-24T10:21:19.0000000+00:00",
      {
        "rps": 381074,
        "avg_latency_ms": 38.73,
        "p99_latency_ms": 1010,
        "cpu_pct": 6252.8,
        "memory_bytes": 907018240,
        "connections": 16384,
        "threads": 64,
        "duration_ms": 5000,
        "pipeline": 1,
        "bandwidth_bps": 610290000,
        "input_bw_bps": 28350000,
        "reconnects": 75476,
        "status_2xx": 1905371,
        "status_3xx": 0,
        "status_4xx": 0,
        "status_5xx": 0
      }
    ],
    [
      "2026-04-26T14:13:04.0000000+00:00",
      {
        "rps": 371108,
        "avg_latency_ms": 39.74,
        "p99_latency_ms": 1040,
        "cpu_pct": 6295.9,
        "memory_bytes": 1008730112,
        "connections": 16384,
        "threads": 64,
        "duration_ms": 5000,
        "pipeline": 1,
        "bandwidth_bps": 594430000,
        "input_bw_bps": 27610000,
        "reconnects": 73485,
        "status_2xx": 1855542,
        "status_3xx": 0,
        "status_4xx": 0,
        "status_5xx": 0
      }
    ]
  ]
}