{
  "data": [
    [
      "2026-03-09T18:05:51.0000000+00:00",
      {
        "rps": 195844,
        "avg_latency_ms": 39.79,
        "p99_latency_ms": 67.3,
        "cpu_pct": 463.6,
        "memory_bytes": 1181116006,
        "connections": 16384,
        "threads": 12,
        "duration_ms": 5000,
        "pipeline": 1,
        "bandwidth_bps": 54300000,
        "input_bw_bps": null,
        "reconnects": 176217,
        "status_2xx": 979220,
        "status_3xx": 0,
        "status_4xx": 494991,
        "status_5xx": 0
      }
    ],
    [
      "2026-03-09T18:39:14.0000000+00:00",
      {
        "rps": 146056,
        "avg_latency_ms": 42.08,
        "p99_latency_ms": 75.1,
        "cpu_pct": 401.1,
        "memory_bytes": 1073741824,
        "connections": 16384,
        "threads": 12,
        "duration_ms": 5000,
        "pipeline": 1,
        "bandwidth_bps": 51300000,
        "input_bw_bps": null,
        "reconnects": 199068,
        "status_2xx": 730281,
        "status_3xx": 0,
        "status_4xx": 561301,
        "status_5xx": 0
      }
    ],
    [
      "2026-03-10T20:09:16.0000000+00:00",
      {
        "rps": 135148,
        "avg_latency_ms": 44.75,
        "p99_latency_ms": 68.8,
        "cpu_pct": 1205.7,
        "memory_bytes": 3865470566,
        "connections": 16384,
        "threads": 64,
        "duration_ms": 5000,
        "pipeline": 1,
        "bandwidth_bps": 47920000,
        "input_bw_bps": null,
        "reconnects": 197298,
        "status_2xx": 677093,
        "status_3xx": 0,
        "status_4xx": 528505,
        "status_5xx": 0
      }
    ],
    [
      "2026-03-12T08:06:25.0000000+00:00",
      {
        "rps": 2178154,
        "avg_latency_ms": 3.93,
        "p99_latency_ms": 19,
        "cpu_pct": 7060.4,
        "memory_bytes": 3865470566,
        "connections": 16384,
        "threads": 64,
        "duration_ms": 5000,
        "pipeline": 1,
        "bandwidth_bps": 465710000,
        "input_bw_bps": null,
        "reconnects": 4492,
        "status_2xx": 10890770,
        "status_3xx": 0,
        "status_4xx": 3048772,
        "status_5xx": 0
      }
    ],
    [
      "2026-03-23T21:22:00.0000000+00:00",
      {
        "rps": 2178154,
        "avg_latency_ms": 3.93,
        "p99_latency_ms": 19,
        "cpu_pct": 7060.4,
        "memory_bytes": 3865470566,
        "connections": 16384,
        "threads": 64,
        "duration_ms": 5000,
        "pipeline": 1,
        "bandwidth_bps": 465710000,
        "input_bw_bps": null,
        "reconnects": 4492,
        "status_2xx": 10890770,
        "status_3xx": 0,
        "status_4xx": 3048772,
        "status_5xx": 0
      }
    ],
    [
      "2026-03-25T00:03:20.0000000+00:00",
      {
        "rps": 2285479,
        "avg_latency_ms": 3.68,
        "p99_latency_ms": 16.8,
        "cpu_pct": 6260.9,
        "memory_bytes": 3865470566,
        "connections": 16384,
        "threads": 64,
        "duration_ms": 5000,
        "pipeline": 1,
        "bandwidth_bps": 404200000,
        "input_bw_bps": 231040000,
        "reconnects": 4479,
        "status_2xx": 11564525,
        "status_3xx": 0,
        "status_4xx": 3200879,
        "status_5xx": 0
      }
    ]
  ]
}