{
  "data": [
    [
      "2026-04-01T09:56:28.0000000+00:00",
      {
        "rps": 22716,
        "avg_latency_ms": 164.04,
        "p99_latency_ms": 652.8,
        "cpu_pct": 10726.5,
        "memory_bytes": 7945689497,
        "connections": 4096,
        "threads": 64,
        "duration_ms": 5000,
        "pipeline": 1,
        "bandwidth_bps": 548450000,
        "input_bw_bps": 1590000000,
        "reconnects": 71692,
        "status_2xx": 340746,
        "status_3xx": 0,
        "status_4xx": 0,
        "status_5xx": 0
      }
    ],
    [
      "2026-04-04T15:52:00.0000000+00:00",
      {
        "rps": 14064,
        "avg_latency_ms": 65.98,
        "p99_latency_ms": 347.5,
        "cpu_pct": 5522.5,
        "memory_bytes": 3113851289,
        "connections": 4096,
        "threads": 64,
        "duration_ms": 5000,
        "pipeline": 1,
        "bandwidth_bps": 409790000,
        "input_bw_bps": 1005430000,
        "reconnects": 41898,
        "status_2xx": 210973,
        "status_3xx": 0,
        "status_4xx": 0,
        "status_5xx": 0
      }
    ]
  ]
}