{
  "data": [
    [
      "2026-03-16T18:24:20.0000000+00:00",
      {
        "rps": 14833,
        "avg_latency_ms": 71.64,
        "p99_latency_ms": 473.2,
        "cpu_pct": 10906.4,
        "memory_bytes": 1825361100,
        "connections": 16384,
        "threads": 64,
        "duration_ms": 5000,
        "pipeline": 1,
        "bandwidth_bps": 476470000,
        "input_bw_bps": 1450000000,
        "reconnects": 16371,
        "status_2xx": 74169,
        "status_3xx": 0,
        "status_4xx": 0,
        "status_5xx": 0
      }
    ],
    [
      "2026-03-23T21:22:00.0000000+00:00",
      {
        "rps": 14833,
        "avg_latency_ms": 71.64,
        "p99_latency_ms": 473.2,
        "cpu_pct": 10906.4,
        "memory_bytes": 1825361100,
        "connections": 16384,
        "threads": 64,
        "duration_ms": 5000,
        "pipeline": 1,
        "bandwidth_bps": 476470000,
        "input_bw_bps": 1450000000,
        "reconnects": 16371,
        "status_2xx": 74169,
        "status_3xx": 0,
        "status_4xx": 0,
        "status_5xx": 0
      }
    ],
    [
      "2026-03-24T22:17:15.0000000+00:00",
      {
        "rps": 15678,
        "avg_latency_ms": 98.87,
        "p99_latency_ms": 703.3,
        "cpu_pct": 9752.8,
        "memory_bytes": 2147483648,
        "connections": 16384,
        "threads": 64,
        "duration_ms": 5000,
        "pipeline": 1,
        "bandwidth_bps": 465610000,
        "input_bw_bps": 1530000000,
        "reconnects": 17372,
        "status_2xx": 78394,
        "status_3xx": 0,
        "status_4xx": 0,
        "status_5xx": 0
      }
    ],
    [
      "2026-03-25T15:43:14.0000000+00:00",
      {
        "rps": 26021,
        "avg_latency_ms": 51.65,
        "p99_latency_ms": 410.5,
        "cpu_pct": 8682.1,
        "memory_bytes": 1932735283,
        "connections": 16384,
        "threads": 64,
        "duration_ms": 5000,
        "pipeline": 1,
        "bandwidth_bps": 1060000000,
        "input_bw_bps": 2540000000,
        "reconnects": 28701,
        "status_2xx": 130107,
        "status_3xx": 0,
        "status_4xx": 0,
        "status_5xx": 0
      }
    ],
    [
      "2026-03-26T08:59:13.0000000+00:00",
      {
        "rps": 26832,
        "avg_latency_ms": 54.55,
        "p99_latency_ms": 584.1,
        "cpu_pct": 9279.5,
        "memory_bytes": 1932735283,
        "connections": 16384,
        "threads": 64,
        "duration_ms": 5000,
        "pipeline": 1,
        "bandwidth_bps": 1080000000,
        "input_bw_bps": 2620000000,
        "reconnects": 87852,
        "status_2xx": 402757,
        "status_3xx": 0,
        "status_4xx": 0,
        "status_5xx": 0
      }
    ]
  ]
}