{
  "data": [
    [
      "2026-03-23T21:22:00.0000000+00:00",
      {
        "rps": 610100,
        "avg_latency_ms": 41.79,
        "p99_latency_ms": 41.79,
        "cpu_pct": 10679,
        "memory_bytes": 13529146982,
        "connections": 256,
        "threads": 64,
        "duration_ms": 5000,
        "pipeline": 1,
        "bandwidth_bps": 9300000000,
        "input_bw_bps": null,
        "reconnects": 0,
        "status_2xx": 3062900,
        "status_3xx": 0,
        "status_4xx": 0,
        "status_5xx": 0
      }
    ],
    [
      "2026-04-03T13:39:11.0000000+00:00",
      {
        "rps": 610100,
        "avg_latency_ms": 41.79,
        "p99_latency_ms": 41.79,
        "cpu_pct": 10679,
        "memory_bytes": 13529146982,
        "connections": 256,
        "threads": 64,
        "duration_ms": 5000,
        "pipeline": 1,
        "bandwidth_bps": 9300000000,
        "input_bw_bps": null,
        "reconnects": 0,
        "status_2xx": 3062900,
        "status_3xx": 0,
        "status_4xx": 0,
        "status_5xx": 0
      }
    ],
    [
      "2026-04-04T15:52:00.0000000+00:00",
      {
        "rps": 465160,
        "avg_latency_ms": 54.8,
        "p99_latency_ms": 54.8,
        "cpu_pct": 6252.7,
        "memory_bytes": 7838315315,
        "connections": 256,
        "threads": 64,
        "duration_ms": 5000,
        "pipeline": 1,
        "bandwidth_bps": 7100000000,
        "input_bw_bps": null,
        "reconnects": 0,
        "status_2xx": 2338500,
        "status_3xx": 0,
        "status_4xx": 0,
        "status_5xx": 0
      }
    ],
    [
      "2026-04-06T15:32:37.0000000+00:00",
      {
        "rps": 469160,
        "avg_latency_ms": 54.42,
        "p99_latency_ms": 54.42,
        "cpu_pct": 6171.7,
        "memory_bytes": 7838315315,
        "connections": 256,
        "threads": 64,
        "duration_ms": 5000,
        "pipeline": 1,
        "bandwidth_bps": 7170000000,
        "input_bw_bps": null,
        "reconnects": 0,
        "status_2xx": 2359300,
        "status_3xx": 0,
        "status_4xx": 0,
        "status_5xx": 0
      }
    ]
  ]
}