{
  "data": [
    [
      "2026-04-21T20:43:48.0000000+00:00",
      {
        "rps": 528420,
        "avg_latency_ms": 0.958,
        "p99_latency_ms": 8.64,
        "cpu_pct": 3508.5,
        "memory_bytes": 9448928051,
        "connections": 512,
        "threads": 64,
        "duration_ms": 5000,
        "pipeline": 1,
        "bandwidth_bps": 79100000,
        "input_bw_bps": 40820000,
        "reconnects": 264110,
        "status_2xx": 2642104,
        "status_3xx": 0,
        "status_4xx": 0,
        "status_5xx": 0
      }
    ],
    [
      "2026-04-26T14:12:38.0000000+00:00",
      {
        "rps": 505087,
        "avg_latency_ms": 1,
        "p99_latency_ms": 9.04,
        "cpu_pct": 3656,
        "memory_bytes": 2899102924,
        "connections": 512,
        "threads": 64,
        "duration_ms": 5000,
        "pipeline": 1,
        "bandwidth_bps": 75600000,
        "input_bw_bps": 39020000,
        "reconnects": 252517,
        "status_2xx": 2525439,
        "status_3xx": 0,
        "status_4xx": 0,
        "status_5xx": 0
      }
    ]
  ]
}