{
  "data": [
    [
      "2026-04-21T20:43:48.0000000+00:00",
      {
        "rps": 576,
        "avg_latency_ms": 55.37,
        "p99_latency_ms": 274.8,
        "cpu_pct": 3155.7,
        "memory_bytes": 66786741452,
        "connections": 32,
        "threads": 64,
        "duration_ms": 5000,
        "pipeline": 1,
        "bandwidth_bps": 91280,
        "input_bw_bps": 4570000000,
        "reconnects": 569,
        "status_2xx": 2881,
        "status_3xx": 0,
        "status_4xx": 0,
        "status_5xx": 0
      }
    ]
  ]
}