{
  "data": [
    [
      "2026-03-08T00:46:01.0000000+00:00",
      {
        "rps": 18853670,
        "avg_latency_ms": 0.026,
        "p99_latency_ms": 0.094,
        "cpu_pct": 1005.7,
        "memory_bytes": 10276044,
        "connections": 16384,
        "threads": 12,
        "duration_ms": 5000,
        "pipeline": 16,
        "bandwidth_bps": null,
        "input_bw_bps": null,
        "reconnects": 0,
        "status_2xx": 0,
        "status_3xx": 0,
        "status_4xx": 0,
        "status_5xx": 0
      }
    ]
  ]
}