{
  "data": [
    [
      "2026-06-15T09:55:54.0000000+00:00",
      {
        "rps": 303451,
        "avg_latency_ms": 13.13,
        "p99_latency_ms": 265.6,
        "cpu_pct": 957.5,
        "memory_bytes": 187695104,
        "connections": 4096,
        "threads": 64,
        "duration_ms": 5000,
        "pipeline": 1,
        "bandwidth_bps": 30960000,
        "input_bw_bps": 23440000,
        "reconnects": 151192,
        "status_2xx": 1517255,
        "status_3xx": 0,
        "status_4xx": 0,
        "status_5xx": 0
      }
    ],
    [
      "2026-06-19T08:29:20.0000000+00:00",
      {
        "rps": 1017605,
        "avg_latency_ms": 4,
        "p99_latency_ms": 40.3,
        "cpu_pct": 2999.6,
        "memory_bytes": 98566144,
        "connections": 4096,
        "threads": 64,
        "duration_ms": 5000,
        "pipeline": 1,
        "bandwidth_bps": 103800000,
        "input_bw_bps": 78610000,
        "reconnects": 508962,
        "status_2xx": 5088028,
        "status_3xx": 0,
        "status_4xx": 0,
        "status_5xx": 0
      }
    ],
    [
      "2026-06-22T10:25:25.0000000+00:00",
      {
        "rps": 1008810,
        "avg_latency_ms": 4.03,
        "p99_latency_ms": 40.6,
        "cpu_pct": 2924.8,
        "memory_bytes": 70254592,
        "connections": 4096,
        "threads": 64,
        "duration_ms": 5000,
        "pipeline": 1,
        "bandwidth_bps": 102910000,
        "input_bw_bps": 77930000,
        "reconnects": 504520,
        "status_2xx": 5044054,
        "status_3xx": 0,
        "status_4xx": 0,
        "status_5xx": 0
      }
    ],
    [
      "2026-06-24T21:55:34.0000000+00:00",
      {
        "rps": 1002791,
        "avg_latency_ms": 4.06,
        "p99_latency_ms": 40.9,
        "cpu_pct": 2911.5,
        "memory_bytes": 109051904,
        "connections": 4096,
        "threads": 64,
        "duration_ms": 5000,
        "pipeline": 1,
        "bandwidth_bps": 102290000,
        "input_bw_bps": 77460000,
        "reconnects": 501399,
        "status_2xx": 5013956,
        "status_3xx": 0,
        "status_4xx": 0,
        "status_5xx": 0
      }
    ],
    [
      "2026-06-28T16:30:51.0000000+00:00",
      {
        "rps": 1019264,
        "avg_latency_ms": 4,
        "p99_latency_ms": 40.2,
        "cpu_pct": 2992.8,
        "memory_bytes": 62914560,
        "connections": 4096,
        "threads": 64,
        "duration_ms": 5000,
        "pipeline": 1,
        "bandwidth_bps": 103980000,
        "input_bw_bps": 78740000,
        "reconnects": 509630,
        "status_2xx": 5096321,
        "status_3xx": 0,
        "status_4xx": 0,
        "status_5xx": 0
      }
    ],
    [
      "2026-06-28T23:21:09.0000000+00:00",
      {
        "rps": 1012911,
        "avg_latency_ms": 4.02,
        "p99_latency_ms": 40.4,
        "cpu_pct": 3045.6,
        "memory_bytes": 104857600,
        "connections": 4096,
        "threads": 64,
        "duration_ms": 5000,
        "pipeline": 1,
        "bandwidth_bps": 103330000,
        "input_bw_bps": 78240000,
        "reconnects": 506548,
        "status_2xx": 5064556,
        "status_3xx": 0,
        "status_4xx": 0,
        "status_5xx": 0
      }
    ],
    [
      "2026-06-30T15:16:05.0000000+00:00",
      {
        "rps": 998522,
        "avg_latency_ms": 4.08,
        "p99_latency_ms": 40.9,
        "cpu_pct": 3054.5,
        "memory_bytes": 257949696,
        "connections": 4096,
        "threads": 64,
        "duration_ms": 5000,
        "pipeline": 1,
        "bandwidth_bps": 101860000,
        "input_bw_bps": 77130000,
        "reconnects": 499284,
        "status_2xx": 4992613,
        "status_3xx": 0,
        "status_4xx": 0,
        "status_5xx": 0
      }
    ]
  ]
}