{
  "data": [
    [
      "2026-04-14T23:25:10.0000000+00:00",
      {
        "rps": 19852,
        "avg_latency_ms": 11.94,
        "p99_latency_ms": 50.1,
        "cpu_pct": 391.9,
        "memory_bytes": 476997222,
        "connections": 256,
        "threads": 64,
        "duration_ms": 5000,
        "pipeline": 1,
        "bandwidth_bps": 101850000,
        "input_bw_bps": 1120000,
        "reconnects": 59522,
        "status_2xx": 297784,
        "status_3xx": 0,
        "status_4xx": 0,
        "status_5xx": 0
      }
    ],
    [
      "2026-04-18T23:55:15.0000000+00:00",
      {
        "rps": 18796,
        "avg_latency_ms": 12.55,
        "p99_latency_ms": 49.8,
        "cpu_pct": 395.4,
        "memory_bytes": 399507456,
        "connections": 256,
        "threads": 64,
        "duration_ms": 5000,
        "pipeline": 1,
        "bandwidth_bps": 96440000,
        "input_bw_bps": null,
        "reconnects": 56327,
        "status_2xx": 281953,
        "status_3xx": 0,
        "status_4xx": 0,
        "status_5xx": 0
      }
    ],
    [
      "2026-04-26T14:13:04.0000000+00:00",
      {
        "rps": 18796,
        "avg_latency_ms": 12.55,
        "p99_latency_ms": 49.8,
        "cpu_pct": 395.4,
        "memory_bytes": 399507456,
        "connections": 256,
        "threads": 64,
        "duration_ms": 5000,
        "pipeline": 1,
        "bandwidth_bps": 96440000,
        "input_bw_bps": null,
        "reconnects": 56327,
        "status_2xx": 281953,
        "status_3xx": 0,
        "status_4xx": 0,
        "status_5xx": 0
      }
    ],
    [
      "2026-05-01T11:42:09.0000000+00:00",
      {
        "rps": 18688,
        "avg_latency_ms": 12.68,
        "p99_latency_ms": 50.2,
        "cpu_pct": 396.1,
        "memory_bytes": 512753664,
        "connections": 256,
        "threads": 64,
        "duration_ms": 5000,
        "pipeline": 1,
        "bandwidth_bps": 96230000,
        "input_bw_bps": 1050000,
        "reconnects": 56044,
        "status_2xx": 280326,
        "status_3xx": 0,
        "status_4xx": 0,
        "status_5xx": 0
      }
    ],
    [
      "2026-05-01T12:47:47.0000000+00:00",
      {
        "rps": 18581,
        "avg_latency_ms": 12.94,
        "p99_latency_ms": 53.4,
        "cpu_pct": 396.3,
        "memory_bytes": 514850816,
        "connections": 256,
        "threads": 64,
        "duration_ms": 5000,
        "pipeline": 1,
        "bandwidth_bps": 95790000,
        "input_bw_bps": 1050000,
        "reconnects": 55738,
        "status_2xx": 278727,
        "status_3xx": 0,
        "status_4xx": 0,
        "status_5xx": 0
      }
    ],
    [
      "2026-05-11T21:15:18.0000000+00:00",
      {
        "rps": 19190,
        "avg_latency_ms": 12.5,
        "p99_latency_ms": 54,
        "cpu_pct": 397.4,
        "memory_bytes": 514850816,
        "connections": 256,
        "threads": 64,
        "duration_ms": 5000,
        "pipeline": 1,
        "bandwidth_bps": 98840000,
        "input_bw_bps": 1080000,
        "reconnects": 57564,
        "status_2xx": 287854,
        "status_3xx": 0,
        "status_4xx": 0,
        "status_5xx": 0
      }
    ],
    [
      "2026-05-13T12:02:20.0000000+00:00",
      {
        "rps": 18581,
        "avg_latency_ms": 12.94,
        "p99_latency_ms": 53.4,
        "cpu_pct": 396.3,
        "memory_bytes": 514850816,
        "connections": 256,
        "threads": 64,
        "duration_ms": 5000,
        "pipeline": 1,
        "bandwidth_bps": 95790000,
        "input_bw_bps": 1050000,
        "reconnects": 55738,
        "status_2xx": 278727,
        "status_3xx": 0,
        "status_4xx": 0,
        "status_5xx": 0
      }
    ],
    [
      "2026-05-18T09:45:13.0000000+00:00",
      {
        "rps": 19646,
        "avg_latency_ms": 12.22,
        "p99_latency_ms": 51.9,
        "cpu_pct": 396,
        "memory_bytes": 511705088,
        "connections": 256,
        "threads": 64,
        "duration_ms": 5000,
        "pipeline": 1,
        "bandwidth_bps": 100910000,
        "input_bw_bps": 1110000,
        "reconnects": 58951,
        "status_2xx": 294704,
        "status_3xx": 0,
        "status_4xx": 0,
        "status_5xx": 0
      }
    ],
    [
      "2026-05-18T11:47:48.0000000+00:00",
      {
        "rps": 18581,
        "avg_latency_ms": 12.94,
        "p99_latency_ms": 53.4,
        "cpu_pct": 396.3,
        "memory_bytes": 514850816,
        "connections": 256,
        "threads": 64,
        "duration_ms": 5000,
        "pipeline": 1,
        "bandwidth_bps": 95790000,
        "input_bw_bps": 1050000,
        "reconnects": 55738,
        "status_2xx": 278727,
        "status_3xx": 0,
        "status_4xx": 0,
        "status_5xx": 0
      }
    ],
    [
      "2026-05-21T13:09:56.0000000+00:00",
      {
        "rps": 19574,
        "avg_latency_ms": 12.05,
        "p99_latency_ms": 52.1,
        "cpu_pct": 396.8,
        "memory_bytes": 512753664,
        "connections": 256,
        "threads": 64,
        "duration_ms": 5000,
        "pipeline": 1,
        "bandwidth_bps": 100620000,
        "input_bw_bps": 1100000,
        "reconnects": 58687,
        "status_2xx": 293611,
        "status_3xx": 0,
        "status_4xx": 0,
        "status_5xx": 0
      }
    ],
    [
      "2026-05-22T10:02:37.0000000+00:00",
      {
        "rps": 18581,
        "avg_latency_ms": 12.94,
        "p99_latency_ms": 53.4,
        "cpu_pct": 396.3,
        "memory_bytes": 514850816,
        "connections": 256,
        "threads": 64,
        "duration_ms": 5000,
        "pipeline": 1,
        "bandwidth_bps": 95790000,
        "input_bw_bps": 1050000,
        "reconnects": 55738,
        "status_2xx": 278727,
        "status_3xx": 0,
        "status_4xx": 0,
        "status_5xx": 0
      }
    ],
    [
      "2026-05-29T12:00:43.0000000+00:00",
      {
        "rps": 18581,
        "avg_latency_ms": 12.94,
        "p99_latency_ms": 53.4,
        "cpu_pct": 396.3,
        "memory_bytes": 514850816,
        "connections": 256,
        "threads": 64,
        "duration_ms": 5000,
        "pipeline": 1,
        "bandwidth_bps": 95790000,
        "input_bw_bps": 1050000,
        "reconnects": 55738,
        "status_2xx": 278727,
        "status_3xx": 0,
        "status_4xx": 0,
        "status_5xx": 0
      }
    ],
    [
      "2026-06-02T16:17:18.0000000+00:00",
      {
        "rps": 19893,
        "avg_latency_ms": 11.79,
        "p99_latency_ms": 53.9,
        "cpu_pct": 396.3,
        "memory_bytes": 546308096,
        "connections": 256,
        "threads": 64,
        "duration_ms": 5000,
        "pipeline": 1,
        "bandwidth_bps": 102230000,
        "input_bw_bps": 1120000,
        "reconnects": 59636,
        "status_2xx": 298405,
        "status_3xx": 0,
        "status_4xx": 0,
        "status_5xx": 0
      }
    ],
    [
      "2026-06-05T09:58:29.0000000+00:00",
      {
        "rps": 18581,
        "avg_latency_ms": 12.94,
        "p99_latency_ms": 53.4,
        "cpu_pct": 396.3,
        "memory_bytes": 514850816,
        "connections": 256,
        "threads": 64,
        "duration_ms": 5000,
        "pipeline": 1,
        "bandwidth_bps": 95790000,
        "input_bw_bps": 1050000,
        "reconnects": 55738,
        "status_2xx": 278727,
        "status_3xx": 0,
        "status_4xx": 0,
        "status_5xx": 0
      }
    ],
    [
      "2026-06-13T21:54:18.0000000+00:00",
      {
        "rps": 18581,
        "avg_latency_ms": 12.94,
        "p99_latency_ms": 53.4,
        "cpu_pct": 396.3,
        "memory_bytes": 514850816,
        "connections": 256,
        "threads": 64,
        "duration_ms": 5000,
        "pipeline": 1,
        "bandwidth_bps": 95790000,
        "input_bw_bps": 1050000,
        "reconnects": 55738,
        "status_2xx": 278727,
        "status_3xx": 0,
        "status_4xx": 0,
        "status_5xx": 0
      }
    ],
    [
      "2026-06-22T00:07:18.0000000+00:00",
      {
        "rps": 18581,
        "avg_latency_ms": 12.94,
        "p99_latency_ms": 53.4,
        "cpu_pct": 396.3,
        "memory_bytes": 514850816,
        "connections": 256,
        "threads": 64,
        "duration_ms": 5000,
        "pipeline": 1,
        "bandwidth_bps": 95790000,
        "input_bw_bps": 1050000,
        "reconnects": 55738,
        "status_2xx": 278727,
        "status_3xx": 0,
        "status_4xx": 0,
        "status_5xx": 0
      }
    ],
    [
      "2026-06-30T15:14:43.0000000+00:00",
      {
        "rps": 18581,
        "avg_latency_ms": 12.94,
        "p99_latency_ms": 53.4,
        "cpu_pct": 396.3,
        "memory_bytes": 514850816,
        "connections": 256,
        "threads": 64,
        "duration_ms": 5000,
        "pipeline": 1,
        "bandwidth_bps": 95790000,
        "input_bw_bps": 1050000,
        "reconnects": 55738,
        "status_2xx": 278727,
        "status_3xx": 0,
        "status_4xx": 0,
        "status_5xx": 0
      }
    ]
  ]
}