{
  "data": [
    [
      "2026-03-29T17:51:26.0000000+00:00",
      {
        "rps": 22777,
        "avg_latency_ms": 399.4,
        "p99_latency_ms": 2029.9999999999998,
        "cpu_pct": 8862.7,
        "memory_bytes": 28668906700,
        "connections": 16384,
        "threads": 64,
        "duration_ms": 5000,
        "pipeline": 1,
        "bandwidth_bps": 997240000,
        "input_bw_bps": 1590000000,
        "reconnects": 107447,
        "status_2xx": 341894,
        "status_3xx": 0,
        "status_4xx": 197261,
        "status_5xx": 0
      }
    ],
    [
      "2026-03-31T16:23:40.0000000+00:00",
      {
        "rps": 31651,
        "avg_latency_ms": 423.15,
        "p99_latency_ms": 2400,
        "cpu_pct": 8775.7,
        "memory_bytes": 26414048870,
        "connections": 16384,
        "threads": 64,
        "duration_ms": 5000,
        "pipeline": 1,
        "bandwidth_bps": 1010740000,
        "input_bw_bps": 2210000000,
        "reconnects": 98229,
        "status_2xx": 475089,
        "status_3xx": 0,
        "status_4xx": 0,
        "status_5xx": 0
      }
    ]
  ]
}