{
  "data": [
    [
      "2026-03-27T09:23:02.0000000+00:00",
      {
        "rps": 27341,
        "avg_latency_ms": 18.58,
        "p99_latency_ms": 20,
        "cpu_pct": 2724.3,
        "memory_bytes": 10952166604,
        "connections": 512,
        "threads": 64,
        "duration_ms": 5000,
        "pipeline": 1,
        "bandwidth_bps": 243460000,
        "input_bw_bps": null,
        "reconnects": 136747,
        "status_2xx": 136705,
        "status_3xx": 0,
        "status_4xx": 0,
        "status_5xx": 0
      }
    ]
  ]
}