{
  "data": [
    [
      "2026-04-29T09:30:06.0000000+00:00",
      {
        "rps": 1112711,
        "avg_latency_ms": 6.16,
        "p99_latency_ms": 6.16,
        "cpu_pct": 6350.8,
        "memory_bytes": 317928243,
        "connections": 6800,
        "threads": 64,
        "duration_ms": 5000,
        "pipeline": 1,
        "bandwidth_bps": null,
        "input_bw_bps": null,
        "reconnects": 0,
        "status_2xx": 5674997,
        "status_3xx": 0,
        "status_4xx": 0,
        "status_5xx": 0
      }
    ],
    [
      "2026-05-11T21:15:18.0000000+00:00",
      {
        "rps": 1112711,
        "avg_latency_ms": 6.16,
        "p99_latency_ms": 6.16,
        "cpu_pct": 6350.8,
        "memory_bytes": 317928243,
        "connections": 6800,
        "threads": 64,
        "duration_ms": 5000,
        "pipeline": 1,
        "bandwidth_bps": null,
        "input_bw_bps": null,
        "reconnects": 0,
        "status_2xx": 5674997,
        "status_3xx": 0,
        "status_4xx": 0,
        "status_5xx": 0
      }
    ]
  ]
}